acace_llm_adapter/__init__.py
acace_llm_adapter-0.1.0.dist-info/METADATA
acace_llm_adapter-0.1.0.dist-info/WHEEL
acace_llm_adapter-0.1.0.dist-info/RECORD
