Metadata-Version: 2.3
Name: acace_llm_adapter
Version: 0.1.0
Summary: LLM adapter utilities for ACACE
Author: ACACE Team
Author-email: team@acace.ai
Requires-Python: >=3.8,<4.0
Classifier: Programming Language :: Python :: 3
Classifier: Programming Language :: Python :: 3.8
Classifier: Programming Language :: Python :: 3.9
Classifier: Programming Language :: Python :: 3.10
Classifier: Programming Language :: Python :: 3.11
Classifier: Programming Language :: Python :: 3.12
Classifier: Programming Language :: Python :: 3.13
Requires-Dist: anthropic (>=0.18.1,<0.19.0)
Requires-Dist: numpy (>=1.26.3,<2.0.0)
Requires-Dist: openai (>=1.12.0,<2.0.0)
